aiodesktop/__init__.py
aiodesktop/browser.py
aiodesktop/compat.py
aiodesktop/resources.py
aiodesktop/server.py
aiodesktop/static/aiodesktop.js
aiodesktop-0.1.3.dist-info/LICENSE
aiodesktop-0.1.3.dist-info/METADATA
aiodesktop-0.1.3.dist-info/WHEEL
aiodesktop-0.1.3.dist-info/top_level.txt
aiodesktop-0.1.3.dist-info/RECORD
