Metadata-Version: 2.1
Name: aiodesktop
Version: 0.1.3
Summary: A set of tools which simplify building cross-platform desktop apps with Python, JavaScript, HTML & CSS.
Home-page: https://github.com/dferens/aiodesktop
Author: Dmitriy Ferens
Author-email: ferensdima@gmail.com
License: UNKNOWN
Keywords: gui,html,javascript,electron,asyncio,websocket
Platform: UNKNOWN
Classifier: Development Status :: 3 - Alpha
Classifier: License :: OSI Approved :: MIT License
Classifier: Operating System :: OS Independent
Classifier: Programming Language :: Python :: 3.6
Classifier: Programming Language :: Python :: 3.7
Classifier: Programming Language :: Python :: 3.8
Classifier: Programming Language :: Python :: 3.9
Requires-Python: >=3.6
Requires-Dist: aiohttp (>=3.1)
Requires-Dist: whichcraft (==0.6.1)
